changelog_builder.py
changelog_builder-0.1.7.dist-info/LICENSE
changelog_builder-0.1.7.dist-info/METADATA
changelog_builder-0.1.7.dist-info/WHEEL
changelog_builder-0.1.7.dist-info/entry_points.txt
changelog_builder-0.1.7.dist-info/top_level.txt
changelog_builder-0.1.7.dist-info/RECORD
