Metadata-Version: 2.1
Name: changelog-builder
Version: 0.1.7
Summary: Tool for creating changelogs
Home-page: https://github.com/RoW171/changelog_builder
Author: Robin 'r0w' Weiland
Author-email: robin.weiland@gmx.de
License: MIT
Keywords: changelog,change,log
Platform: UNKNOWN
Classifier: Development Status :: 5 - Production/Stable
Classifier: Intended Audience :: Developers
Classifier: Topic :: Software Development
Classifier: License :: OSI Approved :: MIT License
Classifier: Programming Language :: Python :: 3.5
Classifier: Programming Language :: Python :: 3.6
Classifier: Programming Language :: Python :: 3.7
Classifier: Programming Language :: Python :: 3.8
Classifier: Programming Language :: Python :: 3.9
Classifier: Operating System :: OS Independent
Requires-Python: >=3.5
